{
  "name": "Southern California Beaches, Mountains, and Attractions",
  "description": "Curated camera-page links. No streams are mirrored or redistributed.",
  "updated": "2026-07-10",
  "cameras": [
    {
      "id": "santa-monica-pier-wheel",
      "name": "Santa Monica Pier \u2014 Pacific Wheel Cam",
      "enabled": true,
      "category": "Beach",
      "latitude": 34.0092,
      "longitude": -118.4976,
      "city": "Santa Monica",
      "county": "Los Angeles",
      "operator": "Pacific Park",
      "description": "Live camera view from the Santa Monica Pier and Pacific Wheel.",
      "pageUrl": "https://pacpark.com/santa-monica-pier-live-cams/",
      "imageUrl": "",
      "streamUrl": "",
      "notes": "Use the operator page; do not cache an expiring player URL."
    },
    {
      "id": "santa-monica-pier-park",
      "name": "Santa Monica Pier \u2014 Park Cam",
      "enabled": true,
      "category": "Tourist Attraction",
      "latitude": 34.0094,
      "longitude": -118.4973,
      "city": "Santa Monica",
      "county": "Los Angeles",
      "operator": "Pacific Park",
      "description": "Sweeping view of Pacific Park, the beach, and pier activity.",
      "pageUrl": "https://pacpark.com/santa-monica-pier-live-cams/park/",
      "imageUrl": "",
      "streamUrl": "",
      "notes": ""
    },
    {
      "id": "santa-monica-pier-pier",
      "name": "Santa Monica Pier \u2014 Pier Cam",
      "enabled": true,
      "category": "Tourist Attraction",
      "latitude": 34.0089,
      "longitude": -118.499,
      "city": "Santa Monica",
      "county": "Los Angeles",
      "operator": "Pacific Park",
      "description": "Live view along the Santa Monica Pier and coastline.",
      "pageUrl": "https://pacpark.com/santa-monica-pier-live-cams/pier/",
      "imageUrl": "",
      "streamUrl": "",
      "notes": ""
    },
    {
      "id": "huntington-beach-city-pier",
      "name": "Huntington Beach City Pier",
      "enabled": true,
      "category": "Beach",
      "latitude": 33.6553,
      "longitude": -118.0038,
      "city": "Huntington Beach",
      "county": "Orange",
      "operator": "City of Huntington Beach",
      "description": "Official city webcam overlooking Huntington Beach Pier.",
      "pageUrl": "https://www.huntingtonbeachca.gov/departments/parks_recreation/beach_information/city_pier_webcam.php",
      "imageUrl": "",
      "streamUrl": "",
      "notes": ""
    },
    {
      "id": "huntington-beach-overview",
      "name": "Huntington Beach Overview",
      "enabled": true,
      "category": "Beach",
      "latitude": 33.6595,
      "longitude": -118.0014,
      "city": "Huntington Beach",
      "county": "Orange",
      "operator": "HBcams",
      "description": "General live view of the beach, pier, weather, and crowds.",
      "pageUrl": "https://hbcams.com/",
      "imageUrl": "",
      "streamUrl": "",
      "notes": ""
    },
    {
      "id": "huntington-beach-north-pier",
      "name": "Huntington Beach \u2014 North of Pier",
      "enabled": true,
      "category": "Beach",
      "latitude": 33.6571,
      "longitude": -118.0042,
      "city": "Huntington Beach",
      "county": "Orange",
      "operator": "HBcams",
      "description": "Live beach and surf view north of Huntington Beach Pier.",
      "pageUrl": "https://hbcams.com/webcams-huntington-beach-north-of-pier/",
      "imageUrl": "",
      "streamUrl": "",
      "notes": ""
    },
    {
      "id": "huntington-beach-surfcity",
      "name": "Huntington Beach \u2014 Surf City USA Cam",
      "enabled": true,
      "category": "Beach",
      "latitude": 33.6549,
      "longitude": -118.005,
      "city": "Huntington Beach",
      "county": "Orange",
      "operator": "Visit Huntington Beach",
      "description": "Surf and weather webcam from the Huntington Beach Pier area.",
      "pageUrl": "https://www.surfcityusa.com/things-to-do/surfing/live-surf-cam/",
      "imageUrl": "",
      "streamUrl": "",
      "notes": ""
    },
    {
      "id": "big-bear-resort-webcams",
      "name": "Big Bear Mountain Resort \u2014 Camera Hub",
      "enabled": true,
      "category": "Mountain",
      "latitude": 34.2364,
      "longitude": -116.889,
      "city": "Big Bear Lake",
      "county": "San Bernardino",
      "operator": "Big Bear Mountain Resort",
      "description": "Official hub for Bear Mountain, Snow Summit, and Snow Valley live cameras.",
      "pageUrl": "https://www.bigbearmountainresort.com/webcams",
      "imageUrl": "",
      "streamUrl": "",
      "notes": ""
    },
    {
      "id": "bear-mountain-base",
      "name": "Bear Mountain \u2014 Base Area",
      "enabled": true,
      "category": "Mountain",
      "latitude": 34.2287,
      "longitude": -116.8613,
      "city": "Big Bear Lake",
      "county": "San Bernardino",
      "operator": "Big Bear Mountain Resort",
      "description": "Live camera views from the Bear Mountain base and terrain.",
      "pageUrl": "https://www.bigbearmountainresort.com/webcams/bear-mountain",
      "imageUrl": "",
      "streamUrl": "",
      "notes": ""
    },
    {
      "id": "bear-mountain-peak",
      "name": "Bear Mountain \u2014 Peak",
      "enabled": true,
      "category": "Mountain",
      "latitude": 34.2188,
      "longitude": -116.8548,
      "city": "Big Bear Lake",
      "county": "San Bernardino",
      "operator": "Big Bear Mountain Resort",
      "description": "Peak and upper-mountain camera views.",
      "pageUrl": "https://www.bigbearmountainresort.com/webcams/bear-mountain",
      "imageUrl": "",
      "streamUrl": "",
      "notes": ""
    },
    {
      "id": "snow-summit-base",
      "name": "Snow Summit \u2014 Base Area",
      "enabled": true,
      "category": "Mountain",
      "latitude": 34.2369,
      "longitude": -116.8895,
      "city": "Big Bear Lake",
      "county": "San Bernardino",
      "operator": "Big Bear Mountain Resort",
      "description": "Live camera from the Snow Summit base area.",
      "pageUrl": "https://www.bigbearmountainresort.com/webcams/snow-summit",
      "imageUrl": "",
      "streamUrl": "",
      "notes": ""
    },
    {
      "id": "snow-summit-miracle-mile",
      "name": "Snow Summit \u2014 Miracle Mile",
      "enabled": true,
      "category": "Mountain",
      "latitude": 34.2315,
      "longitude": -116.885,
      "city": "Big Bear Lake",
      "county": "San Bernardino",
      "operator": "Big Bear Mountain Resort",
      "description": "Live upper-slope view near Miracle Mile.",
      "pageUrl": "https://www.bigbearmountainresort.com/webcams/snow-summit",
      "imageUrl": "",
      "streamUrl": "",
      "notes": ""
    },
    {
      "id": "snow-valley-base",
      "name": "Snow Valley \u2014 Base Area",
      "enabled": true,
      "category": "Mountain",
      "latitude": 34.2248,
      "longitude": -117.0364,
      "city": "Running Springs",
      "county": "San Bernardino",
      "operator": "Big Bear Mountain Resort",
      "description": "Live Snow Valley base-area conditions.",
      "pageUrl": "https://www.bigbearmountainresort.com/webcams/snow-valley",
      "imageUrl": "",
      "streamUrl": "",
      "notes": ""
    },
    {
      "id": "snow-valley-peak",
      "name": "Snow Valley \u2014 Peak",
      "enabled": true,
      "category": "Mountain",
      "latitude": 34.2169,
      "longitude": -117.0275,
      "city": "Running Springs",
      "county": "San Bernardino",
      "operator": "Big Bear Mountain Resort",
      "description": "Live upper-mountain and peak conditions.",
      "pageUrl": "https://www.bigbearmountainresort.com/webcams/snow-valley",
      "imageUrl": "",
      "streamUrl": "",
      "notes": ""
    },
    {
      "id": "big-bear-valley-weather-cams",
      "name": "Big Bear Valley Weather Cameras",
      "enabled": true,
      "category": "Mountain",
      "latitude": 34.2439,
      "longitude": -116.9114,
      "city": "Big Bear Lake",
      "county": "San Bernardino",
      "operator": "BensWeather",
      "description": "Collection of Big Bear Valley weather and mountain cameras.",
      "pageUrl": "https://www.bensweather.com/wxwebcams.php",
      "imageUrl": "",
      "streamUrl": "",
      "notes": ""
    },
    {
      "id": "socal-mountain-webcam-directory",
      "name": "Southern California Mountain Webcam Directory",
      "enabled": true,
      "category": "Mountain",
      "latitude": 34.243,
      "longitude": -116.911,
      "city": "Big Bear Lake",
      "county": "San Bernardino",
      "operator": "MTN WebCams",
      "description": "Directory of Big Bear, Lake Arrowhead, Running Springs, and nearby mountain webcams.",
      "pageUrl": "https://mtnwebcams.com/",
      "imageUrl": "",
      "streamUrl": "",
      "notes": "Directory link; individual camera entries can be added after manual verification."
    }
  ]
}
